apache_airflow_providers_duckdb-0.1.1.dist-info/licenses/LICENSE
duckdb_provider/__init__.py
duckdb_provider/hooks/__init__.py
duckdb_provider/hooks/duckdb_hook.py
apache_airflow_providers_duckdb-0.1.1.dist-info/METADATA
apache_airflow_providers_duckdb-0.1.1.dist-info/WHEEL
apache_airflow_providers_duckdb-0.1.1.dist-info/entry_points.txt
apache_airflow_providers_duckdb-0.1.1.dist-info/top_level.txt
apache_airflow_providers_duckdb-0.1.1.dist-info/RECORD
