Metadata-Version: 2.4
Name: apache-airflow-providers-duckdb
Version: 0.1.1
Summary: DuckDB (duckdb.org) provider for Apache Airflow
Author-email: Your Name <schapman1974@gmail.com>
License: Apache License 2.0
Project-URL: Homepage, https://your-url.com
Classifier: Framework :: Apache Airflow
Classifier: Framework :: Apache Airflow :: Provider
Requires-Python: >=3.8
License-File: LICENSE
Requires-Dist: apache-airflow>=2.0
Requires-Dist: duckdb>=0.5.0
Dynamic: license-file
